VERSION
autocomplete.bash
autocomplete.zsh
klogin.py
profiles
klogin-0.8.4.dist-info/entry_points.txt
klogin-0.8.4.dist-info/WHEEL
klogin-0.8.4.dist-info/METADATA
klogin-0.8.4.dist-info/RECORD
