Metadata-Version: 2.1
Name: klogin
Version: 0.8.4
Summary: 
Author: Logi Leifsson
Author-email: logi@genuitysci.com
Requires-Python: >=3.8,<3.12
Classifier: Programming Language :: Python :: 3
Classifier: Programming Language :: Python :: 3.8
Classifier: Programming Language :: Python :: 3.9
Classifier: Programming Language :: Python :: 3.10
Classifier: Programming Language :: Python :: 3.11
